xontrib/free_cwd.py
xontrib_free_cwd-0.0.1.dist-info/LICENSE
xontrib_free_cwd-0.0.1.dist-info/METADATA
xontrib_free_cwd-0.0.1.dist-info/WHEEL
xontrib_free_cwd-0.0.1.dist-info/top_level.txt
xontrib_free_cwd-0.0.1.dist-info/RECORD
