Metadata-Version: 2.1
Name: xontrib-free-cwd
Version: 0.0.1
Summary: To release the lock on the current directory whenever the prompt is shown in xonsh shell. Windows only xontrib.
Author-email: xontrib-free-cwd <no@no.no>
License: MIT License
Project-URL: Homepage, https://github.com/xonsh/xontrib-free-cwd
Project-URL: Documentation, https://github.com/xonsh/xontrib-free-cwd/blob/master/README.md
Project-URL: Code, https://github.com/xonsh/xontrib-free-cwd
Project-URL: Issue tracker, https://github.com/xonsh/xontrib-free-cwd/issues
Platform: any
Classifier: Programming Language :: Python :: 3
Classifier: License :: OSI Approved :: MIT License
Classifier: Operating System :: OS Independent
Classifier: Topic :: System :: Shells
Classifier: Topic :: System :: System Shells
Classifier: Topic :: Terminals
Requires-Python: >=3.8
License-File: LICENSE
Requires-Dist: xonsh (>=0.12.5)
Provides-Extra: dev
Requires-Dist: pytest (>=7.0) ; extra == 'dev'
